rad/__init__.py
rad/_version.py
rad/integration.py
rad/resources/__init__.py
rad/resources/manifests/datamodels-1.0.yaml
rad/resources/schemas/aperture-1.0.0.yaml
rad/resources/schemas/basic-1.0.0.yaml
rad/resources/schemas/cal_logs-1.0.0.yaml
rad/resources/schemas/cal_step-1.0.0.yaml
rad/resources/schemas/common-1.0.0.yaml
rad/resources/schemas/coordinates-1.0.0.yaml
rad/resources/schemas/ephemeris-1.0.0.yaml
rad/resources/schemas/exposure-1.0.0.yaml
rad/resources/schemas/exposure_type-1.0.0.yaml
rad/resources/schemas/guidestar-1.0.0.yaml
rad/resources/schemas/guidewindow-1.0.0.yaml
rad/resources/schemas/guidewindow_modes-1.0.0.yaml
rad/resources/schemas/observation-1.0.0.yaml
rad/resources/schemas/photometry-1.0.0.yaml
rad/resources/schemas/pixelarea-1.0.0.yaml
rad/resources/schemas/pointing-1.0.0.yaml
rad/resources/schemas/program-1.0.0.yaml
rad/resources/schemas/rad_schema-1.0.0.yaml
rad/resources/schemas/ramp-1.0.0.yaml
rad/resources/schemas/ramp_fit_output-1.0.0.yaml
rad/resources/schemas/ref_file-1.0.0.yaml
rad/resources/schemas/target-1.0.0.yaml
rad/resources/schemas/variance-1.0.0.yaml
rad/resources/schemas/velocity_aberration-1.0.0.yaml
rad/resources/schemas/visit-1.0.0.yaml
rad/resources/schemas/wcsinfo-1.0.0.yaml
rad/resources/schemas/wfi_detector-1.0.0.yaml
rad/resources/schemas/wfi_image-1.0.0.yaml
rad/resources/schemas/wfi_mode-1.0.0.yaml
rad/resources/schemas/wfi_optical_element-1.0.0.yaml
rad/resources/schemas/wfi_science_raw-1.0.0.yaml
rad/resources/schemas/reference_files/dark-1.0.0.yaml
rad/resources/schemas/reference_files/distortion-1.0.0.yaml
rad/resources/schemas/reference_files/flat-1.0.0.yaml
rad/resources/schemas/reference_files/gain-1.0.0.yaml
rad/resources/schemas/reference_files/linearity-1.0.0.yaml
rad/resources/schemas/reference_files/mask-1.0.0.yaml
rad/resources/schemas/reference_files/pixelarea-1.0.0.yaml
rad/resources/schemas/reference_files/readnoise-1.0.0.yaml
rad/resources/schemas/reference_files/ref_common-1.0.0.yaml
romanad-0.11.1.dist-info/LICENSE
romanad-0.11.1.dist-info/METADATA
romanad-0.11.1.dist-info/WHEEL
romanad-0.11.1.dist-info/entry_points.txt
romanad-0.11.1.dist-info/top_level.txt
romanad-0.11.1.dist-info/zip-safe
romanad-0.11.1.dist-info/RECORD
