Metadata-Version: 2.1
Name: romanad
Version: 0.11.1
Summary: romanad is now rad
Home-page: https://github.com/spacetelescope/rad
Author: STScI
License: BSD-3-Clause
Project-URL: Bug Tracker, https://github.com/spacetelescope/rad/issues
Project-URL: Source Code, https://github.com/spacetelescope/rad
Platform: UNKNOWN
Classifier: Development Status :: 7 - Inactive
Requires-Python: >=3.6
License-File: LICENSE
Requires-Dist: rad
Provides-Extra: test
Requires-Dist: pytest (>=4.6.0) ; extra == 'test'
Requires-Dist: pytest-openfiles (>=0.5.0) ; extra == 'test'
